chonky/__init__.py
chonky/markup_remover.py
chonky/test_markup_remover.py
chonky-0.1.7.dist-info/METADATA
chonky-0.1.7.dist-info/WHEEL
chonky-0.1.7.dist-info/licenses/LICENSE
chonky-0.1.7.dist-info/RECORD
