Metadata-Version: 2.4
Name: chonky
Version: 0.1.7
Summary: Chonky is a Python library that intelligently segments text into meaningful semantic chunks using a fine-tuned transformer model.
Project-URL: Homepage, https://github.com/mirth/chonky
Project-URL: Issues, https://github.com/mirth/chonky/issues
Author: mirth
License-Expression: MIT
License-File: LICENSE
Keywords: NLP,RAG,text splitter
Classifier: Intended Audience :: Developers
Classifier: Intended Audience :: Education
Classifier: Intended Audience :: Science/Research
Classifier: Operating System :: OS Independent
Classifier: Programming Language :: Python :: 3
Classifier: Topic :: Scientific/Engineering :: Artificial Intelligence
Requires-Python: >=3.9
Requires-Dist: transformers
